[{"wp_inactive_widgets":["archives-2","paperio_twitter_widget-3","paperio_popular_post_widget-5","mc4wp_form_widget-4","paperio_instagram_widget-10"],"sidebar-1":["paperio_about_widget-2","paperio_follow_us_widget-4","mc4wp_form_widget-2","categories-3","paperio_popular_post_widget-2","tag_cloud-4","paperio_favourite_quotes_widget-2","paperio_ads_widget-2"],"menu-banner1":["text-3"],"menu-banner2":["text-4"],"left-sidebar":["search-2","paperio_popular_post_widget-4"],"right-sidebar":["paperio_recent_menu_post_widget-2"],"footer-sidebar-1":["paperio_about_widget-3"],"footer-sidebar-2":["paperio_twitter_widget-2"],"footer-sidebar-3":["paperio_instagram_widget-9"]},{"paperio_about_widget":{"2":{"title":"About Me","tz_author_image_url":"http:\/\/wpdemos.themezaa.com\/paperio\/demo-images\/2016\/06\/350X264-ph.jpg","tz_image_link_url":"#","tz_author_image_alt":"About Me","tz_author_name":"John Doe","tz_author_short_description":"<p class=\"text-small padding-four-top xs-padding-two-top no-margin-bottom\">Lorem Ipsum is simply dummy text of the printing and typesetting industry. Lorem Ipsum has been industry's standard.<\/p>"},"3":{"title":"About Me","tz_author_image_url":"http:\/\/wpdemos.themezaa.com\/paperio\/demo-images\/360x150.jpg","tz_image_link_url":"http:\/\/wpdemos.themezaa.com\/paperio\/aquilina\/about-me\/","tz_author_image_alt":"About me","tz_author_name":"","tz_author_short_description":"Lorem Ipsum is simply dummy text of the printing and typesetting industry. Lorem Ipsum has been industry's standard. Lorem Ipsum is simply dummy text of the printing and typesetting industry. Lorem Ipsum has been industry's standard."},"_multiwidget":1},"paperio_follow_us_widget":{"4":{"title":"Follow Us","follow_facebook":"#","follow_twitter":"#","follow_gplus":"#","follow_bloglovin":"#","follow_pinterest":"#","follow_instagram":"#","follow_tumblr":"","follow_youtube":"","follow_dribble":"","follow_soundcloud":"","follow_vimeo":"","follow_linkedin":"","follow_rss":""},"_multiwidget":1},"mc4wp_form_widget":{"2":{"title":"Newsletter"},"4":[],"_multiwidget":1},"categories":{"3":{"title":"Categories","count":1,"hierarchical":0,"dropdown":0},"_multiwidget":1},"paperio_popular_post_widget":{"2":{"title":"Popular Post","tz_popular_post_date_format":"M d, Y","tz_popular_post_orderby":"date","tz_popular_post_sortby":"DESC","tz_popular_post_postperpage":"4","tz_popular_post_thumbnail":"on"},"4":{"title":"Popular Post","tz_popular_post_date_format":"F j, Y","tz_popular_post_orderby":"date","tz_popular_post_sortby":"DESC","tz_popular_post_postperpage":"4","tz_popular_post_thumbnail":""},"5":{"title":"Popular Post","tz_popular_post_date_format":"F j, Y","tz_popular_post_orderby":"date","tz_popular_post_sortby":"DESC","tz_popular_post_postperpage":"4","tz_popular_post_thumbnail":"on"},"_multiwidget":1},"tag_cloud":{"4":{"title":"Tag Cloud","taxonomy":"post_tag"},"_multiwidget":1},"paperio_favourite_quotes_widget":{"2":{"title":"Favourite Quotes","short_description":"My favorite things in life don't cost any money. It's really clear that the most precious resource we all have is time.","author_name":"- STEVE JOBS"},"_multiwidget":1},"paperio_ads_widget":{"2":{"title":"","tz_ads_image_url":"http:\/\/wpdemos.themezaa.com\/paperio\/demo-images\/2016\/06\/800X533-ph.jpg","tz_ads_image_link_url":"#","tz_ads_image_alt":"Ads Banner","tz_ads_shortcode":""},"_multiwidget":1},"text":{"3":{"title":"","text":"<img alt=\"\" src=\"http:\/\/wpdemos.themezaa.com\/paperio\/demo-images\/2016\/11\/ad-banner1.jpg\">","filter":false},"4":{"title":"","text":"<img alt=\"\" src=\"http:\/\/wpdemos.themezaa.com\/paperio\/demo-images\/2016\/11\/ad-banner2.jpg\">","filter":false},"_multiwidget":1},"search":{"2":{"title":"Search"},"_multiwidget":1},"paperio_recent_menu_post_widget":{"2":{"title":"Recent Post","tz_column_type":"four-column","tz_recent_category":"all","tz_recent_category_orderby":"date","tz_recent_category_sortby":"DESC","postperpage":"4","thumbnail":"on"},"_multiwidget":1},"paperio_twitter_widget":{"2":{"title":"Recent Tweets","tz_twitter_user_name":"devtesting2013","tz_twitter_consumer_key":"DcStNIyc35QhTozeTj5txqs9X","tz_twitter_consumer_secret":"I0ZxdrI1BTQwkglNR1y5OKCcHTCcUiDZzz7xC6IJ76s5VPT1sw","tz_twitter_access_token":"1059576889-YS8ghCw7EkANbQW6O3eT7zzlYvwOF6cehyZ7v0F","tz_twitter_access_token_secret":"FdBjKJvvLpNey72xZKOj0yUik9uMCHIXHhhXZDDid4Zcx","tz_twitter_tweet_limit":"3"},"3":{"title":"Recent Tweets","tz_twitter_user_name":"devtesting2013","tz_twitter_consumer_key":"DcStNIyc35QhTozeTj5txqs9X","tz_twitter_consumer_secret":"I0ZxdrI1BTQwkglNR1y5OKCcHTCcUiDZzz7xC6IJ76s5VPT1sw","tz_twitter_access_token":"1059576889-YS8ghCw7EkANbQW6O3eT7zzlYvwOF6cehyZ7v0F","tz_twitter_access_token_secret":"FdBjKJvvLpNey72xZKOj0yUik9uMCHIXHhhXZDDid4Zcx","tz_twitter_tweet_limit":"8"},"_multiwidget":1},"paperio_instagram_widget":{"9":{"title":"Instagram","tz_small_title_text":"","tz_title_text":"","instagram_access_token":"3907141248.1677ed0.d25a6e3b075a46aa8594fd276ae90a74","instagram_id":"3907141248","instagram_style":"grid-style","instagram_feed_autoplay":"yes","instagram_feed_speed":"9000","instagram_feed_stop_on_hover":"no","show_instagram_pagination":"false","instagram_pagination_style":"owl-dot-pagination","instagram_pagination_color":"pagination-dark-style","instagram_cursor_style_color":"owl-cursor-default","no_of_columns_instagram_feed":"4","no_instagram_feed_desktop":"8","no_instagram_feed_desktop_mini":"4","no_instagram_feed_ipad":"2","no_instagram_feed_mobile":"1","sort_instagram_feed":"none","no_instagram_feed":"12","disable_instagram_like":""},"10":{"title":"Follow Us @ Instagram","tz_small_title_text":"Find Me on","tz_title_text":"Follow Us @ Instagram","instagram_access_token":"2207153490.1677ed0.e37a84336e65454f9ed48542f62a2b6a","instagram_id":"2207153490","instagram_style":"grid-style","instagram_feed_autoplay":"no","instagram_feed_speed":"3000","instagram_feed_stop_on_hover":"no","show_instagram_pagination":"false","instagram_pagination_style":"owl-dot-pagination","instagram_pagination_color":"pagination-dark-style","instagram_cursor_style_color":"owl-cursor-default","no_of_columns_instagram_feed":"","no_instagram_feed_desktop":"4","no_instagram_feed_ipad":"2","no_instagram_feed_mobile":"1","sort_instagram_feed":"none","no_instagram_feed":"10","disable_instagram_like":""},"_multiwidget":1},"archives":{"2":{"title":"Archives","count":0,"dropdown":0},"_multiwidget":1}}]